pef_krushna.py
pef_krushna-0.1.dist-info/LICENSE
pef_krushna-0.1.dist-info/WHEEL
pef_krushna-0.1.dist-info/METADATA
pef_krushna-0.1.dist-info/RECORD
