Metadata-Version: 2.1
Name: pef_krushna
Version: 0.1
Summary: pef uninstall pip-installed package with all its dependencies.
Home-page: https://github.com/nalangekrushna/pef_krushna
License: UNKNOWN
Author: krushnakumar nalange
Author-email: nalangekrushna@gmail.com
Classifier: License :: OSI Approved :: Apache Software License
